pyssair.py
pyssair-0.1.0a0.dist-info/licenses/LICENSE
pyssair-0.1.0a0.dist-info/METADATA
pyssair-0.1.0a0.dist-info/WHEEL
pyssair-0.1.0a0.dist-info/top_level.txt
pyssair-0.1.0a0.dist-info/RECORD
