Metadata-Version: 2.4
Name: pyssair
Version: 0.1.0a0
Summary: A first-of-its-kind project that faithfully converts Python bytecode into a static single assignment (SSA)-like intermediate representation (IR) for program analysis.
Author-email: Jifeng Wu <jifengwu2k@gmail.com>
License-Expression: Apache-2.0
Project-URL: Homepage, https://github.com/jifengwu2k/pyssair
Project-URL: Bug Tracker, https://github.com/jifengwu2k/pyssair/issues
Classifier: Programming Language :: Python :: 3.12
Requires-Python: ==3.12
License-File: LICENSE
Requires-Dist: networkx
Requires-Dist: put-back-iterator
Dynamic: license-file
